Edge_Detect_Pos_Or_Neg/Edge_Detect_Pos_Or_Neg.srcs/sources_1/new/Edge_Detect.v
`timescale 1ns / 1ps
// Code your design here
module Edge_Detect ( input sig,            // Input signal for which positive edge has to be detected
                      input clk,            // Input signal for clock
                      output pe);           // Output signal that gives a pulse when a positive edge occurs
 
    reg   sig_dly;                          // Internal signal to store the delayed version of signal
    reg [3:0]count=0;
     //This always block ensures that sig_dly is exactly 1 clock behind sig
  always @ (posedge clk) begin
    sig_dly <= sig;
    
  end
 
    // Combinational logic where sig is AND with delayed, inverted version of sig
    // Assign statement assigns the evaluated expression in the RHS to the internal net pe
  assign pe = sig & ~sig_dly;    
  always@(posedge pe) // to count no of pulses received
  begin
  count=count+1;
  end        
endmodule 

//Following code is tried to detect edges but it will not work as it only detecting level of pulses at posedge of clock.So for edge detection above code will be used.
//Although it will detect posede but count is going up at levels.
//Check differenc of both at 46ns in Simulation waveform
// always@(posedge clk)
// begin 
// if(sig)
// begin
//   sig_dly=1;
//  count=count+1;
//end
//  else
//  sig_dly=0;
//end
//endmodule

Edge_Detect_Pos_Or_Neg/Edge_Detect_Pos_Or_Neg.srcs/sim_1/new/Edge_Detect_tb.v
`timescale 1ns / 1ps
module Edge_Detect_tb;
	reg sig;                                  // Declare internal TB signal called sig to drive the sig pin of the design
	reg clk;                                  // Declare internal TB signal called clk to drive clock to the design
	
	// Instantiate the design in TB and connect with signals in TB
	Edge_Detect uut (  .sig(sig),           
    					 .clk(clk),
 			      		 .pe(pe));

	// Generate a clock of 100MHz
	always #5 clk = ~clk;           
	
	// Drive stimulus to the design
	initial begin
		clk <= 0;
		sig <= 0;
		#11 sig <= 1;
		#20 sig <= 0;
		#15 sig <= 1;
		#10 sig <= 0;
		#20 $finish;
	end	
  
  	initial begin
      	$dumpvars;
      $dumpfile("dump.vcd");
    end
endmodule

Edge_Detect_Pos_Or_Neg/Edge_Detect_Pos_Or_Neg.sim/sim_1/behav/xsim/dump.vcd
$date
   Mon Aug 26 10:28:25 2024
$end
$version
  2018.2
$end
$timescale
  1ps
$end
$scope module Edge_Detect_tb $end
$var reg 1 ! sig $end
$var reg 1 " clk $end
$var wire 1 # pe $end
$scope module uut $end
$var wire 1 $ sig $end
$var wire 1 % clk $end
$var wire 1 # pe $end
$var reg 1 & sig_dly $end
$var reg 4 ' count [3:0] $end
$upscope $end
$upscope $end
$enddefinitions $end
#0
$dumpvars
0!
0"
0#
0$
0%
x&
b0 '
$end
#5000
1"
0#
1%
0&
#10000
0"
0%
#11000
1!
1#
1$
b1 '
#15000
1"
0#
1%
1&
#20000
0"
0%
#25000
1"
1%
1&
#30000
0"
0%
#31000
0!
0#
0$
#35000
1"
0#
1%
0&
#40000
0"
0%
#45000
1"
1%
0&
#46000
1!
1#
1$
b10 '
#50000
0"
0%
#55000
1"
0#
1%
1&
#56000
0!
0#
0$
#60000
0"
0%
#65000
1"
0#
1%
0&
#70000
0"
0%
#75000
1"
1%
0&
